{"ewV3rLjABLfWObyVvBqKTQ==":"mbr-1-1618x1080.jpg","/I6KLdhsclqHTUMU9fyttw==":"mbr-6-1620x1080.jpg","OqMYApgTGTtmNy50AY/8Jw==":"mbr-7-1620x1080.jpg","EcdVM3suuwMUp9X/hoY3DA==":"mbr-9-1620x1080.jpg","nS+/qlXbnSEY/AqpYnCDdQ==":"mbr-10-1620x1080.jpg","5vmwcmVrxauJKoMpvOlkhw==":"mbr-1438x1080.jpg","cFNhFjOOTVfjL/J9RKX1Ig==":"background4.jpg","I8/dxHwHSIbFh8hytzulIg==":"body-of-water-3098951-1920-1920x1280.jpg","k2m676LiExIX7K6ltt2FjQ==":"renda-extra-numo-up-capa-1920x1280.jpg","JWIsFO0iUdgymk2FrHps8A==":"woman-3094278-1920-1920x1280.jpg","Q9H6HgKCsj+iTNUeR1UzOQ==":"engagement-1718244-1920-1920x1280.jpg","0jFkSa9AeF0bmMJDQSwS0Q==":"renda-extra-numo-up-casal-capa-inicio-1920x1280.jpg","igJYoR9n4wWY/14/jSBl0g==":"mbr-721x1080.jpg","Vrzym/U2oscsG1kPV6aLfA==":"mbr-1620x1080.jpg","k/q0heGwK8NviELZdcGFgg==":"mbr-1-1620x1080.jpg","P5PaHaA7v29DzgZrz/ZTXg==":"numoup-renda-extra-logo-220x220.png","gUXaH4R1A+y6A9l46oDLVw==":"mbr-1619x1080.jpg","4CLuzWy+TQuq0avHh2SR0A==":"numoup-renda-extra-logo-1-220x220.png","uIOhaMjxEwXOl6oAPjEUmg==":"meseems-507x570.jpg","7fBhM4uG5vaD3+PtGWGKNQ==":"2-300x230.png","aifjsRpLHUgiobrysXeEwA==":"mbr-2-1620x1080.jpg","4DE9E+nkkWY2yQ4dmgYViQ==":"woman-1979272_1920%20(1)-1920x1280.jpg","1K+D+z1pdQUcFUdX9X86lw==":"woman-3083379-1920-1920x1280.jpg","PZV/f8ZDl8zDpwye8Gr0uw==":"mbr-3-1620x1080.jpg","HCaGroLK2GA2LNeoTNYrSg==":"mbr-4-1620x1080.jpg","JdvzNZqmmoWwgECC84/xAw==":"mbr-5-1620x1080.jpg","7BIhO0LEMd1B7haUSddbug==":"family-591581-1920-1920x1280.jpg","oQHdl6zmi/lzR1In6cufRQ==":"joy-2483926-1920-1920x1281.jpg","qPISTjxCdnfM2kDvydDnyg==":"mbr-1618x1080.jpg","PupQEpCQuKYGOwuwcGKnQQ==":"agreement-2548138-1280-1280x854.jpg","ZRAj4yzilrOPdCWq1CBqSA==":"tablet-313002-1920-1920x1378.jpg","SCXW4NEGf0jzT/VV6CEILQ==":"smartphone-1894723-1920-1920x1280.jpg","YFuDtSPRSCaHljLqWTqCbw==":"agreement-2548138-1281-1280x854.jpg","4T+hrUgZkoPJHoCYkZpkoQ==":"mbr-8-1620x1080.jpg","ZAFtE3++7rV57da7YoFZRA==":"mbr-11-1620x1080.jpg","HY1K0kHGCO9kEmMCtsfIXA==":"numoup-renda-extra-logo-2-220x220.png","TdbPjgGOOthGB5L431JZtg==":"mbr-2-1618x1080.jpg","GM+1utpxe2zzEMxdiD0pWw==":"11-336x280.png","kWPbjPoAp6I7lgT3OLbEsA==":"1-336x280.png","UPGN5jtD0ItPDENV4Acz0Q==":"2-336x280.png","rFxxDc0hYOffWh81KNj6DA==":"4-336x280.png","ZLciC5BThY6XpDpCkjVIxg==":"8-336x280.png","IU0t9ei2iLsmWMTZMPzfEQ==":"7-336x280.png","0VazViwx1ujuR8UNB81HZQ==":"mbr-3-1618x1080.jpg","VdA028PX0RrFqEOPs/OM8Q==":"mbr-12-1620x1080.jpg","ArQdcdqCinnfFn/IFWD/nQ==":"mbr-13-1620x1080.jpg","s0m+LEKxBSHpQ+WNa+drmA==":"mbr-1424x1080.jpg","n0/tg0Yeq8F5d9huT4MVWQ==":"mbr-1-1438x1080.jpg"}